MANIFEST.in
README.rst
setup.py
apache/busmon.wsgi
busmon/__init__.py
busmon/__init__.pyc
busmon/widgets.py
busmon/widgets.pyc
busmon.egg-info/PKG-INFO
busmon.egg-info/SOURCES.txt
busmon.egg-info/dependency_links.txt
busmon.egg-info/entry_points.txt
busmon.egg-info/not-zip-safe
busmon.egg-info/paster_plugins.txt
busmon.egg-info/requires.txt
busmon.egg-info/top_level.txt
busmon/config/__init__.py
busmon/config/__init__.pyc
busmon/config/app_cfg.py
busmon/config/app_cfg.pyc
busmon/config/deployment.ini_tmpl
busmon/config/environment.py
busmon/config/environment.pyc
busmon/config/middleware.py
busmon/config/middleware.pyc
busmon/controllers/__init__.py
busmon/controllers/__init__.pyc
busmon/controllers/error.py
busmon/controllers/error.pyc
busmon/controllers/root.py
busmon/controllers/root.pyc
busmon/controllers/secure.py
busmon/controllers/template.py
busmon/i18n/ru/LC_MESSAGES/busmon.po
busmon/lib/__init__.py
busmon/lib/__init__.pyc
busmon/lib/app_globals.py
busmon/lib/app_globals.pyc
busmon/lib/base.py
busmon/lib/base.pyc
busmon/lib/helpers.py
busmon/lib/helpers.pyc
busmon/public/favicon.ico
busmon/public/css/960_24_col.css
busmon/public/css/monokai.css
busmon/public/css/site.css
busmon/public/css/text.css
busmon/public/css/voting.css
busmon/public/css/fonts/Cantarell-Bold-webfont.eot
busmon/public/css/fonts/Cantarell-Bold-webfont.svg
busmon/public/css/fonts/Cantarell-Bold-webfont.ttf
busmon/public/css/fonts/Cantarell-Bold-webfont.woff
busmon/public/css/fonts/Cantarell-BoldOblique-webfont.eot
busmon/public/css/fonts/Cantarell-BoldOblique-webfont.svg
busmon/public/css/fonts/Cantarell-BoldOblique-webfont.ttf
busmon/public/css/fonts/Cantarell-BoldOblique-webfont.woff
busmon/public/css/fonts/Cantarell-Oblique-webfont.eot
busmon/public/css/fonts/Cantarell-Oblique-webfont.svg
busmon/public/css/fonts/Cantarell-Oblique-webfont.ttf
busmon/public/css/fonts/Cantarell-Oblique-webfont.woff
busmon/public/css/fonts/Cantarell-Regular-webfont.eot
busmon/public/css/fonts/Cantarell-Regular-webfont.svg
busmon/public/css/fonts/Cantarell-Regular-webfont.ttf
busmon/public/css/fonts/Cantarell-Regular-webfont.woff
busmon/public/css/fonts/Comfortaa_Bold-webfont.eot
busmon/public/css/fonts/Comfortaa_Bold-webfont.svg
