Metadata-Version: 1.0
Name: busmon
Version: 0.4.6
Summary: A webapp for visualizing activity on the Fedora Message Bus.
Home-page: http://github.com/ralphbean/busmon
Author: Ralph Bean
Author-email: rbean@redhat.com
License: GPLv2+
Platform: UNKNOWN
